Metadata-Version: 2.1
Name: JsOnXmLSe814Rializer749
Version: 1.0
Summary: Serializer
Home-page: UNKNOWN
Author-email: tatarinov.slava222@gmail.com
License: UNKNOWN
Platform: UNKNOWN
